Workbook

Sheet Flujo
C2: 24 | P2: 25 | AB2: 27 | AN2: 28 | AZ2: 29 | BL2: 30 | BX2: 31 | CJ2: 32 | CV2: 33 | DH2: 34 | DT2: 35 | EF2: 36 | ER2: 37 | FD2: 38 | FP2: 39 | FQ2: 40 | FR2: 41 | FS2: 42 | FT2: 43 | FU2: 44 | FV2: 45 | FW2: 46 | FX2: 47 | FY2: 48 | FZ2: 49 | GA2: 50 | GB2: 51 | GC2: 52 | GD2: 53 | GE2: 54 | GF2: 55 | GG2: 56 | GH2: 57 | GI2: 58 | GJ2: 59 | GK2: 60 | GL2: 61 | GM2: 62 | GN2: 63 | GO2: 64 | GP2: 65 | GQ2: 66 | GR2: 67 | GS2: 68 | GT2: 69 | GU2: 70 | GV2: 71 | GW2: 72 | GX2: 73 | GY2: 74 | GZ2: 75 | HA2: 76 | HB2: 77 | HC2: 78 | HD2: 79 | HE2: 80 | HF2: 81 | HG2: 82 | HH2: 83 | HI2: 84 | HJ2: 85 | HK2: 86 | HL2: 87 | HM2: 88
C3: 44927 | D3: 44958 | E3: 44986 | F3: 45017 | G3: 45047 | H3: 45078 | I3: 45108 | J3: Mes Control | K3: 45139 | L3: 45170 | M3: 45200 | N3: 45231 | O3: 45261 | P3: 45292 | Q3: 45323 | R3: 45352 | S3: 45383 | T3: 45413 | U3: 45444 | V3: 45474 | W3: 45505 | X3: 45536 | Y3: 45566 | Z3: 45597 | AA3: 45627 | AB3: 45658 | AC3: 45689 | AD3: 45717 | AE3: 45748 | AF3: 45778 | AG3: 45809 | AH3: 45839 | AI3: 45870 | AJ3: 45901 | AK3: 45931 | AL3: 45962 | AM3: 45992 | AN3: 46023 | AO3: 46054 | AP3: 46082 | AQ3: 46113 | AR3: 46143 | AS3: 46174 | AT3: 46204 | AU3: 46235 | AV3: 46266 | AW3: 46296 | AX3: 46327 | AY3: 46357 | AZ3: 46388 | BA3: 46419 | BB3: 46447 | BC3: 46478 | BD3: 46508 | BE3: 46539 | BF3: 46569 | BG3: 46600 | BH3: 46631 | BI3: 46661 | BJ3: 46692 | BK3: 46722 | BL3: 46753 | BM3: 46784 | BN3: 46813 | BO3: 46844 | BP3: 46874 | BQ3: 46905 | BR3: 46935 | BS3: 46966 | BT3: 46997 | BU3: 47027 | BV3: 47058 | BW3: 47088 | BX3: 47119 | BY3: 47150 | BZ3: 47178 | CA3: 47209 | CB3: 47239 | CC3: 47270 | CD3: 47300 | CE3: 47331 | CF3: 47362 | CG3: 47392 | CH3: 47423 | CI3: 47453 | CJ3: 47484 | CK3: 47515 | CL3: 47543 | CM3: 47574 | CN3: 47604 | CO3: 47635 | CP3: 47665 | CQ3: 47696 | CR3: 47727 | CS3: 47757 | CT3: 47788 | CU3: 47818 | CV3: 47849 | CW3: 47880 | CX3: 47908 | CY3: 47939 | CZ3: 47969 | DA3: 48000 | DB3: 48030 | DC3: 48061 | DD3: 48092 | DE3: 48122 | DF3: 48153 | DG3: 48183 | DH3: 48214 | DI3: 48245 | DJ3: 48274 | DK3: 48305 | DL3: 48335 | DM3: 48366 | DN3: 48396 | DO3: 48427 | DP3: 48458 | DQ3: 48488 | DR3: 48519 | DS3: 48549 | DT3: 48580 | DU3: 48611 | DV3: 48639 | DW3: 48670 | DX3: 48700 | DY3: 48731 | DZ3: 48761 | EA3: 48792 | EB3: 48823 | EC3: 48853 | ED3: 48884 | EE3: 48914 | EF3: 48945 | EG3: 48976 | EH3: 49004 | EI3: 49035 | EJ3: 49065 | EK3: 49096 | EL3: 49126 | EM3: 49157 | EN3: 49188 | EO3: 49218 | EP3: 49249 | EQ3: 49279 | ER3: 49310 | ES3: 49341 | ET3: 49369 | EU3: 49400 | EV3: 49430 | EW3: 49461 | EX3: 49491 | EY3: 49522 | EZ3: 49553 | FA3: 49583 | FB3: 49614 | FC3: 49644 | FD3: 49675 | FE3: 49706 | FF3: 49735 | FG3: 49766 | FH3: 49796 | FI3: 49827 | FJ3: 49857 | FK3: 49888 | FL3: 49919 | FM3: 49949 | FN3: 49980 | FO3: 50010 | FP3: TA | FQ3: TA | FR3: TA | FS3: TA | FT3: TA | FU3: TA | FV3: TA | FW3: TA | FX3: TA | FY3: TA | FZ3: TA | GA3: TA | GB3: TA | GC3: TA | GD3: TA | GE3: TA | GF3: TA | GG3: TA | GH3: TA | GI3: TA | GJ3: TA | GK3: TA | GL3: TA | GM3: TA | GN3: TA | GO3: TA | GP3: TA | GQ3: TA | GR3: TA | GS3: TA | GT3: TA | GU3: TA | GV3: TA | GW3: TA | GX3: TA | GY3: TA | GZ3: TA | HA3: TA | HB3: TA | HC3: TA | HD3: TA | HE3: TA | HF3: TA | HG3: TA | HH3: TA | HI3: TA | HJ3: TA | HK3: TA | HL3: TA | HM3: TA
B4: Ingreso 1 | C4: 750000 | D4: 750000 | E4: 750000 | F4: 750000 | G4: 750000 | H4: 750000 | I4: 750000 | K4: 750000 | L4: =+K4 -> 750000 | M4: =+L4 -> 750000 | N4: =+M4 -> 750000 | O4: =+N4 -> 750000 | P4: 750000 | Q4: =+P4 -> 750000 | R4: =+Q4 -> 750000 | S4: =+R4 -> 750000 | T4: =+S4 -> 750000 | U4: =+T4 -> 750000 | V4: =+U4 -> 750000 | W4: =+V4 -> 750000 | X4: =+W4 -> 750000 | ... FO4: =+FN4 -> 750000 | FP4: =SUM(FD4:FO4) -> 9000000 | FQ4: =+FP4 -> 9000000 | FR4: =+FQ4 -> 9000000 | FS4: =+FR4 -> 9000000 | FT4: =+FS4 -> 9000000 | FU4: =+FT4 -> 9000000 | FV4: =+FU4 -> 9000000 | FW4: =+FV4 -> 9000000 | FX4: =+FW4 -> 9000000 | ... HM4: =+HL4 -> 9000000
B5: Ingreso 2 | L5: =+K5 -> 0 | M5: =+L5 -> 0 | N5: =+M5 -> 0 | O5: =+N5 -> 0 | P5: =+O5 -> 0 | Q5: =+P5 -> 0 | R5: =+Q5 -> 0 | S5: =+R5 -> 0 | ... FO5: =+FN5 -> 0 | FP5: =SUM(FD5:FO5) -> 0 | FQ5: =+FP5 -> 0 | FR5: =+FQ5 -> 0 | FS5: =+FR5 -> 0 | FT5: =+FS5 -> 0 | FU5: =+FT5 -> 0 | FV5: =+FU5 -> 0 | FW5: =+FV5 -> 0 | FX5: =+FW5 -> 0 | ... HM5: =+HL5 -> 0
B7: Total Ingreso | C7: =SUM(C4:C5) -> 750000 | D7: =SUM(D4:D5) -> 750000 | E7: =SUM(E4:E5) -> 750000 | F7: =SUM(F4:F5) -> 750000 | G7: =SUM(G4:G5) -> 750000 | H7: =SUM(H4:H5) -> 750000 | I7: =SUM(I4:I5) -> 750000 | K7: =SUM(K4:K6) -> 750000 | L7: =SUM(L4:L6) -> 750000 | M7: =SUM(M4:M6) -> 750000 | N7: =SUM(N4:N6) -> 750000 | O7: =SUM(O4:O6) -> 750000 | P7: =SUM(P4:P6) -> 750000 | Q7: =SUM(Q4:Q6) -> 750000 | R7: =SUM(R4:R6) -> 750000 | ... HM7: =SUM(HM4:HM6) -> 9000000
B9: Arriendo/Div | C9: -250000 | D9: -250000 | E9: -250000 | F9: -250000 | G9: -250000 | H9: -250000 | I9: -250000 | K9: -250000 | L9: =+K9 -> -250000 | M9: =+L9 -> -250000 | N9: =+M9 -> -250000 | O9: =+N9 -> -250000 | P9: -250000 | Q9: =+P9 -> -250000 | R9: =+Q9 -> -250000 | S9: =+R9 -> -250000 | T9: =+S9 -> -250000 | U9: =+T9 -> -250000 | V9: =+U9 -> -250000 | W9: =+V9 -> -250000 | X9: =+W9 -> -250000 | ... FO9: =+FN9 -> -250000 | FP9: =SUM(FD9:FO9) -> -3000000 | FQ9: =+FP9 -> -3000000 | FR9: =+FQ9 -> -3000000 | FS9: =+FR9 -> -3000000 | FT9: =+FS9 -> -3000000 | FU9: =+FT9 -> -3000000 | FV9: =+FU9 -> -3000000 | FW9: =+FV9 -> -3000000 | FX9: =+FW9 -> -3000000 | ... HM9: =+HL9 -> -3000000
B10: Gasto Comun | C10: -40000 | D10: -40000 | E10: -40000 | F10: -40000 | G10: -40000 | H10: -40000 | I10: -40000 | K10: -40000 | L10: =+K10 -> -40000 | M10: =+L10 -> -40000 | N10: =+M10 -> -40000 | O10: =+N10 -> -40000 | P10: =+O10 -> -40000 | Q10: =+P10 -> -40000 | R10: =+Q10 -> -40000 | S10: =+R10 -> -40000 | ... FO10: =+FN10 -> -40000 | FP10: =SUM(FD10:FO10) -> -480000 | FQ10: =+FP10 -> -480000 | FR10: =+FQ10 -> -480000 | FS10: =+FR10 -> -480000 | FT10: =+FS10 -> -480000 | FU10: =+FT10 -> -480000 | FV10: =+FU10 -> -480000 | FW10: =+FV10 -> -480000 | FX10: =+FW10 -> -480000 | ... HM10: =+HL10 -> -480000
B11: Supermercado | C11: -200000 | D11: -200000 | E11: -200000 | F11: -200000 | G11: -200000 | H11: -200000 | I11: -200000 | K11: -200000 | L11: =+K11 -> -200000 | M11: =+L11 -> -200000 | N11: =+M11 -> -200000 | O11: =+N11 -> -200000 | P11: =+O11 -> -200000 | Q11: =+P11 -> -200000 | R11: =+Q11 -> -200000 | S11: =+R11 -> -200000 | ... FO11: =+FN11 -> -200000 | FP11: =SUM(FD11:FO11) -> -2400000 | FQ11: =+FP11 -> -2400000 | FR11: =+FQ11 -> -2400000 | FS11: =+FR11 -> -2400000 | FT11: =+FS11 -> -2400000 | FU11: =+FT11 -> -2400000 | FV11: =+FU11 -> -2400000 | FW11: =+FV11 -> -2400000 | FX11: =+FW11 -> -2400000 | ... HM11: =+HL11 -> -2400000
B12: Transporte | C12: -40000 | D12: -40000 | E12: -40000 | F12: -40000 | G12: -40000 | H12: -40000 | I12: -40000 | K12: -40000 | L12: =+K12 -> -40000 | M12: =+L12 -> -40000 | N12: =+M12 -> -40000 | O12: =+N12 -> -40000 | P12: =+O12 -> -40000 | Q12: =+P12 -> -40000 | R12: =+Q12 -> -40000 | S12: =+R12 -> -40000 | ... FO12: =+FN12 -> -40000 | FP12: =SUM(FD12:FO12) -> -480000 | FQ12: =+FP12 -> -480000 | FR12: =+FQ12 -> -480000 | FS12: =+FR12 -> -480000 | FT12: =+FS12 -> -480000 | FU12: =+FT12 -> -480000 | FV12: =+FU12 -> -480000 | FW12: =+FV12 -> -480000 | FX12: =+FW12 -> -480000 | ... HM12: =+HL12 -> -480000
B15: Total Gastos Fijos | C15: =SUM(C8:C14) -> -530000 | D15: =SUM(D8:D14) -> -530000 | E15: =SUM(E8:E14) -> -530000 | F15: =SUM(F8:F14) -> -530000 | G15: =SUM(G8:G14) -> -530000 | H15: =SUM(H8:H14) -> -530000 | I15: =SUM(I8:I14) -> -530000 | K15: =SUM(K8:K14) -> -530000 | L15: =SUM(L8:L14) -> -530000 | M15: =SUM(M8:M14) -> -530000 | N15: =SUM(N8:N14) -> -530000 | O15: =SUM(O8:O14) -> -530000 | P15: =SUM(P8:P14) -> -530000 | Q15: =SUM(Q8:Q14) -> -530000 | R15: =SUM(R8:R14) -> -530000 | ... HM15: =SUM(HM8:HM14) -> -6360000
B18: Recreacional Otros | C18: -100000 | D18: -100000 | E18: -100000 | F18: -100000 | G18: -100000 | H18: -100000 | I18: -100000 | K18: -100000 | L18: =-100000+50000 -> -50000 | M18: =-100000+50000 -> -50000 | N18: =-100000+50000 -> -50000 | O18: -100000 | P18: =+O18 -> -100000 | Q18: =+P18 -> -100000 | R18: =+Q18 -> -100000 | S18: =+R18 -> -100000 | T18: =+S18 -> -100000 | U18: =+T18 -> -100000 | V18: =+U18 -> -100000 | W18: =+V18 -> -100000 | ... FO18: =+FN18 -> -100000 | FP18: =SUM(FD18:FO18) -> -1200000 | FQ18: =+FP18 -> -1200000 | FR18: =+FQ18 -> -1200000 | FS18: =+FR18 -> -1200000 | FT18: =+FS18 -> -1200000 | FU18: =+FT18 -> -1200000 | FV18: =+FU18 -> -1200000 | FW18: =+FV18 -> -1200000 | FX18: =+FW18 -> -1200000 | ... HM18: =+HL18 -> -1200000
B19: TC | K19: =+TC!J12 -> 0 | L19: =+TC!K12 -> -50000 | M19: =+TC!L12 -> -50000 | N19: =+TC!M12 -> -50000 | O19: =+TC!N12 -> 0 | P19: =+TC!O12 -> 0 | Q19: =+TC!P12 -> 0 | R19: =+TC!Q12 -> 0 | ... FO19: =+TC!FN12 -> 0
B20: Ropa | C20: -50000 | D20: -50000 | E20: -50000 | F20: -50000 | G20: -50000 | H20: -50000 | I20: -50000 | K20: -50000 | L20: =+K20 -> -50000 | M20: =+L20 -> -50000 | N20: =+M20 -> -50000 | O20: =+N20 -> -50000 | P20: =+O20 -> -50000 | Q20: =+P20 -> -50000 | R20: =+Q20 -> -50000 | S20: =+R20 -> -50000 | ... FO20: =+FN20 -> -50000 | FP20: =SUM(FD20:FO20) -> -600000 | FQ20: =+FP20 -> -600000 | FR20: =+FQ20 -> -600000 | FS20: =+FR20 -> -600000 | FT20: =+FS20 -> -600000 | FU20: =+FT20 -> -600000 | FV20: =+FU20 -> -600000 | FW20: =+FV20 -> -600000 | FX20: =+FW20 -> -600000 | ... HM20: =+HL20 -> -600000
B21: Vacaciones | L21: =+K21 -> 0 | M21: =+L21 -> 0 | N21: =+M21 -> 0 | O21: -700000 | AA21: -700000 | AM21: -700000 | AY21: -700000 | BK21: -700000 | BW21: -700000 | CI21: -700000 | CU21: -700000 | DG21: -700000 | DS21: -700000 | EE21: -700000 | EQ21: -700000 | FC21: -700000 | FO21: -700000 | FP21: =SUM(FD21:FO21) -> -700000 | FQ21: =+FP21 -> -700000 | FR21: =+FQ21 -> -700000 | FS21: =+FR21 -> -700000 | FT21: =+FS21 -> -700000 | FU21: =+FT21 -> -700000 | FV21: =+FU21 -> -700000 | FW21: =+FV21 -> -700000 | FX21: =+FW21 -> -700000 | ... HM21: =+HL21 -> -700000
B24: Total Gastos Variables | C24: =SUM(C16:C23) -> -150000 | D24: =SUM(D16:D23) -> -150000 | E24: =SUM(E16:E23) -> -150000 | F24: =SUM(F16:F23) -> -150000 | G24: =SUM(G16:G23) -> -150000 | H24: =SUM(H16:H23) -> -150000 | I24: =SUM(I16:I23) -> -150000 | J24: =SUM(J16:J23) -> 0 | ... HM24: =SUM(HM16:HM23) -> -2500000
B26: Total Gastos F+V | C26: =C15+C24 -> -680000 | D26: =D15+D24 -> -680000 | E26: =E15+E24 -> -680000 | F26: =F15+F24 -> -680000 | G26: =G15+G24 -> -680000 | H26: =H15+H24 -> -680000 | I26: =I15+I24 -> -680000 | J26: =J15+J24 -> 0 | K26: =+K15+K24 -> -680000 | L26: =+L15+L24 -> -680000 | M26: =+M15+M24 -> -680000 | N26: =+N15+N24 -> -680000 | O26: =+O15+O24 -> -1380000 | P26: =+P15+P24 -> -680000 | Q26: =+Q15+Q24 -> -680000 | R26: =+R15+R24 -> -680000 | ... HM26: =+HM15+HM24 -> -8860000
B29: Flujo Mes | C29: =C7+C26 -> 70000 | D29: =D7+D26 -> 70000 | E29: =E7+E26 -> 70000 | F29: =F7+F26 -> 70000 | G29: =G7+G26 -> 70000 | H29: =H7+H26 -> 70000 | I29: =I7+I26 -> 70000 | J29: =J7+J26 -> 0 | K29: =+K7+K26 -> 70000 | L29: =+L7+L26 -> 70000 | M29: =+M7+M26 -> 70000 | N29: =+N7+N26 -> 70000 | O29: =+O7+O26 -> -630000 | P29: =+P7+P26 -> 70000 | Q29: =+Q7+Q26 -> 70000 | R29: =+R7+R26 -> 70000 | ... HM29: =+HM7+HM26 -> 140000
B30: Flujo Acumulado Mes | C30: =+C29 -> 70000 | D30: =C30+D29 -> 140000 | E30: =D30+E29 -> 210000 | F30: =E30+F29 -> 280000 | G30: =F30+G29 -> 350000 | H30: =G30+H29 -> 420000 | I30: =H30+I29 -> 490000 | J30: =I30+J29 -> 490000 | K30: =+J30+K29 -> 560000 | L30: =+K30+L29 -> 630000 | M30: =+L30+M29 -> 700000 | N30: =+M30+N29 -> 770000 | O30: =+N30+O29 -> 140000 | P30: =+O30+P29 -> 210000 | Q30: =+P30+Q29 -> 280000 | R30: =+Q30+R29 -> 350000 | ... HM30: =+HL30+HM29 -> 8960000
I33: Efectivo | J33: 50000 | K33: 50000 | L33: =+J33-K33 -> 0 | N33: Meta | O33: 140000
I34: Banco | J34: 440000 | K34: 370000 | L34: =+J34-K34 -> 70000 | N34: Delta | O34: =+O30-O33 -> 0
I35: Total | J35: =+J33+J34 -> 490000 | K35: =+K33+K34 -> 420000 | L35: =+L33+L34 -> 70000
I36: Validador | J36: =+J35-I30 -> 0

Sheet TC
C2: 25 | O2: 26 | AA2: 27 | AM2: 28 | AY2: 29 | BK2: 30 | BW2: 31 | CI2: 32 | CU2: 33 | DG2: 34 | DS2: 35 | EE2: 36 | EQ2: 37 | FC2: 38 | FO2: 39 | FP2: 40 | FQ2: 41 | FR2: 42 | FS2: 43 | FT2: 44 | FU2: 45 | FV2: 46 | FW2: 47 | FX2: 48 | FY2: 49 | FZ2: 50 | GA2: 51 | GB2: 52 | GC2: 53 | GD2: 54 | GE2: 55 | GF2: 56 | GG2: 57 | GH2: 58 | GI2: 59 | GJ2: 60 | GK2: 61 | GL2: 62 | GM2: 63 | GN2: 64 | GO2: 65 | GP2: 66 | GQ2: 67 | GR2: 68 | GS2: 69 | GT2: 70 | GU2: 71 | GV2: 72 | GW2: 73 | GX2: 74 | GY2: 75 | GZ2: 76 | HA2: 77 | HB2: 78 | HC2: 79 | HD2: 80 | HE2: 81 | HF2: 82 | HG2: 83 | HH2: 84 | HI2: 85 | HJ2: 86 | HK2: 87 | HL2: 88
C3: 44927 | D3: 44958 | E3: 44986 | F3: 45017 | G3: 45047 | H3: 45078 | I3: 45108 | J3: 45139 | K3: 45170 | L3: 45200 | M3: 45231 | N3: 45261 | O3: 45292 | P3: 45323 | Q3: 45352 | R3: 45383 | S3: 45413 | T3: 45444 | U3: 45474 | V3: 45505 | W3: 45536 | X3: 45566 | Y3: 45597 | Z3: 45627 | AA3: 45658 | AB3: 45689 | AC3: 45717 | AD3: 45748 | AE3: 45778 | AF3: 45809 | AG3: 45839 | AH3: 45870 | AI3: 45901 | AJ3: 45931 | AK3: 45962 | AL3: 45992 | AM3: 46023 | AN3: 46054 | AO3: 46082 | AP3: 46113 | AQ3: 46143 | AR3: 46174 | AS3: 46204 | AT3: 46235 | AU3: 46266 | AV3: 46296 | AW3: 46327 | AX3: 46357 | AY3: 46388 | AZ3: 46419 | BA3: 46447 | BB3: 46478 | BC3: 46508 | BD3: 46539 | BE3: 46569 | BF3: 46600 | BG3: 46631 | BH3: 46661 | BI3: 46692 | BJ3: 46722 | BK3: 46753 | BL3: 46784 | BM3: 46813 | BN3: 46844 | BO3: 46874 | BP3: 46905 | BQ3: 46935 | BR3: 46966 | BS3: 46997 | BT3: 47027 | BU3: 47058 | BV3: 47088 | BW3: 47119 | BX3: 47150 | BY3: 47178 | BZ3: 47209 | CA3: 47239 | CB3: 47270 | CC3: 47300 | CD3: 47331 | CE3: 47362 | CF3: 47392 | CG3: 47423 | CH3: 47453 | CI3: 47484 | CJ3: 47515 | CK3: 47543 | CL3: 47574 | CM3: 47604 | CN3: 47635 | CO3: 47665 | CP3: 47696 | CQ3: 47727 | CR3: 47757 | CS3: 47788 | CT3: 47818 | CU3: 47849 | CV3: 47880 | CW3: 47908 | CX3: 47939 | CY3: 47969 | CZ3: 48000 | DA3: 48030 | DB3: 48061 | DC3: 48092 | DD3: 48122 | DE3: 48153 | DF3: 48183 | DG3: 48214 | DH3: 48245 | DI3: 48274 | DJ3: 48305 | DK3: 48335 | DL3: 48366 | DM3: 48396 | DN3: 48427 | DO3: 48458 | DP3: 48488 | DQ3: 48519 | DR3: 48549 | DS3: 48580 | DT3: 48611 | DU3: 48639 | DV3: 48670 | DW3: 48700 | DX3: 48731 | DY3: 48761 | DZ3: 48792 | EA3: 48823 | EB3: 48853 | EC3: 48884 | ED3: 48914 | EE3: 48945 | EF3: 48976 | EG3: 49004 | EH3: 49035 | EI3: 49065 | EJ3: 49096 | EK3: 49126 | EL3: 49157 | EM3: 49188 | EN3: 49218 | EO3: 49249 | EP3: 49279 | EQ3: 49310 | ER3: 49341 | ES3: 49369 | ET3: 49400 | EU3: 49430 | EV3: 49461 | EW3: 49491 | EX3: 49522 | EY3: 49553 | EZ3: 49583 | FA3: 49614 | FB3: 49644 | FC3: 49675 | FD3: 49706 | FE3: 49735 | FF3: 49766 | FG3: 49796 | FH3: 49827 | FI3: 49857 | FJ3: 49888 | FK3: 49919 | FL3: 49949 | FM3: 49980 | FN3: 50010 | FO3: TA | FP3: TA | FQ3: TA | FR3: TA | FS3: TA | FT3: TA | FU3: TA | FV3: TA | FW3: TA | FX3: TA | FY3: TA | FZ3: TA | GA3: TA | GB3: TA | GC3: TA | GD3: TA | GE3: TA | GF3: TA | GG3: TA | GH3: TA | GI3: TA | GJ3: TA | GK3: TA | GL3: TA | GM3: TA | GN3: TA | GO3: TA | GP3: TA | GQ3: TA | GR3: TA | GS3: TA | GT3: TA | GU3: TA | GV3: TA | GW3: TA | GX3: TA | GY3: TA | GZ3: TA | HA3: TA | HB3: TA | HC3: TA | HD3: TA | HE3: TA | HF3: TA | HG3: TA | HH3: TA | HI3: TA | HJ3: TA | HK3: TA | HL3: TA
B5: G1 | I5: 0 | K5: -50000 | L5: -50000 | M5: -50000
B6: G2
B7: G3
B8: G4
B12: Total Gastos Fijos | C12: =SUM(C4:C11) -> 0 | D12: =SUM(D4:D11) -> 0 | E12: =SUM(E4:E11) -> 0 | F12: =SUM(F4:F11) -> 0 | G12: =SUM(G4:G11) -> 0 | H12: =SUM(H4:H11) -> 0 | I12: =SUM(I4:I11) -> 0 | J12: =SUM(J4:J11) -> 0 | ... HL12: =SUM(HL4:HL11) -> 0
